setup.py
shri_probability/Binomialdistribution.py
shri_probability/Gaussiandistribution.py
shri_probability/Generaldistribution.py
shri_probability/__init__.py
shri_probability.egg-info/PKG-INFO
shri_probability.egg-info/SOURCES.txt
shri_probability.egg-info/dependency_links.txt
shri_probability.egg-info/not-zip-safe
shri_probability.egg-info/top_level.txt