Metadata-Version: 1.0
Name: shri-probability
Version: 0.1
Summary: Gaussian and Binomial distributions
Home-page: UNKNOWN
Author: Shridhar Sundaram
Author-email: myemail@gmail.com
License: UNKNOWN
Platform: UNKNOWN
